<?xml version="1.0" encoding="utf-8" ?>
<elements>
  <info>
    <name>Chronomancer</name>
    <description>The Chronomancer class by reddit user Zst0rm.</description>
    <author url="https://www.reddit.com/r/UnearthedArcana/comments/3vhk15/5e_chronomancer_entire_class/">Reddit user Zst0rm</author>
    <update version="0.2.8">
      <file name="class-chronomancer.xml" url="https://raw.githubusercontent.com/aurorabuilder/elements/master/core/players-handbook/classes/class-Chronomancer.xml" />
    </update>
  </info>

 <element name="Chronomancer" type="Class" source="Zst0rm" id="ID_ZSTORM_REDDIT_CLASS_CHRONOMANCER">
    <description>
      <p>Existence is measured in age. How many years has a mortal lived? What was the construction date of the walled city of Ambrosia? When were the deities formed? Time begins at birth, at creation. But, inevitably, time for all things comes to an end.</p>
      <p class="indent">Except, of course, for time itself.</p>
      <p class="indent">Bearer of the clock of eternity, rimmed by signs of the Zodiac, the chronomancer counts every tick of the second hand, preventing interference with that essential ever flowing forward momentum.</p>
      <h4>RELEVANCE OF TIME</h4>
      <p>Chronomancers gain their magical potency directly from time itself - harnessing the energies of flowing time, and manipulating them to suit their gain.</p>
      <p class="indent">It is a most dangerous tradition, as the practice of slowing, reversing, or diverting the flow of time can accidently tear novices to pieces, spreading them thinly across millennia, or sometimes even drop them wholesale into a new or old era, with no way of returning home.</p>
      <p class="indent">Masters, however, walk the generations as planeswalkers walk the cosmos. Experienced chronomancers can reliably and literally end most conflicts before th most conflicts before they even begin.</p>
      <p class="indent">Chronomancers typically learn to control their powers through an eternity of studies, usually under the guidance of an older mentor. However there is no greater test than altering reality. Many aspiring chronomancers test their newly honed powers by changing the outcome of a significant event by travelling through different timelines to craft the most favored result.</p>
      <h4>CREATING A Chronomancer </h4>
      <p>As you build your chronomancer, think about when and why your character pursued the ebband flow of time. Did the thought of changing a significant event in the past plague you as a young adult and it was not until you matured that you realised bending time was the best way to correct the wron to correct the wrong-doing you had done? Maybe you were cursed with these powers by a demon, forced to endure visions of a million possible ways for your closest friend to die every night, only relieiving you of the curse if you craft the best possible outcome.</p>
      <p class="indent">Consider how your character perceives their abilities. Do abilities. Do you view them as a punishment for a wrong-doing from a long time ago? Or maybe view them as gift from your deity to protect and assist those around you.</p>
      <h5>QUICK BUILD</h5>
      <p>You can make a chronomancer quickly by following these suggestions. Firstly, Wisdom should be your highest ability score, followed by Constitution &amp; Intelligence. Secondly, choose the Sage background. Thirdly, take the cantrips <i>Prestidigitation</i>, <i>Bolt of Prestidigitation</i>, <i>Bolt of Time</i>.</p>
      <p class="indent">Along with the following 1st level spells: <i>Magic Missile</i> and <i>Feather Fall</i></p>
      <h3>CLASS FEATURES</h3>
      <p>As a Chronomancer, you gain the following class features.</p>
      <h5>HIT POINTS</h5>
      <p>
        <span class="emphasis">Hit Dice:</span>1d6 per Chronomancer level<br/>
        <span class="emphasis">Hit Points at 1st Level:</span>6 + your Constitution modifier<br/>
        <span class="emphasis">Hit Points at Higher Levels:</span>1d6 (or 4) + your Constitution modifier per Chronomancer level after 1st<br/>
      </p>
      <h5>PROFICIENCIES</h5>
      <p>
        <span class="emphasis">Armor:</span>Light Armor, shields<br/>
        <span class="emphasis">Weapons:</span>Dagger, quarterstaff, shortsword<br/>
        <span class="emphasis">Tools:</span>Gaming set<br/>
      </p>
      <p>
        <span class="emphasis">Saving Throws:</span>Intelligence, Wisdom<br/>
        <span class="emphasis">Skills:</span>Choose two from Arcana, History, Insight, Investigation, Perception, Persuasion and Religion<br/>
      </p>
      <h5>EQUIPMENT</h5>
      <p>You start with the following equipment, in addition to the equipment granted by your background:</p>
      <ul>
        <li>(a) Two shortswords or (b) a shortsword and shield</li>
        <li>A quarterstaff and light armor</li>
        <li>Your choice of gamig set</li>
        <li>An ancient tome and explorer's pack</li>
      </ul>
      <div element="ID_ZSTORM_REDDIT_CLASS_FEATURE_CHRONOMANCER_SPELLCASTING_CHRONOMANCER" />
      <div element="ID_ZSTORM_REDDIT_CLASS_FEATURE_CHRONOMANCER_AGELESS_LINGUISTICS" />
      <div element="ID_ZSTORM_REDDIT_CLASS_FEATURE_CHRONOMANCER_WHEEL_OF_TIME" />
      <div element="ID_ZSTORM_REDDIT_CLASS_FEATURE_CHRONOMANCER_TIMELESS_BODY" />
      <div element="ID_ZSTORM_REDDIT_CLASS_FEATURE_CHRONOMANCER_LIFELONG_JOURNEY" />
      <div element="ID_ZSTORM_REDDIT_CLASS_FEATURE_CHRONOMANCER_ABILITYSCOREIMPROVEMENT_CHRONOMANCER" />
      <div element="ID_ZSTORM_REDDIT_CLASS_FEATURE_CHRONOMANCER_POCKET_OF_ETERNITY" />
      <div element="ID_ZSTORM_REDDIT_CLASS_FEATURE_CHRONOMANCER_LIFELONG_JOURNEY_FEATURE" />
      <div element="ID_ZSTORM_REDDIT_CLASS_FEATURE_CHRONOMANCER_AGELESS_LINGUISTICS_FEATURE" />
      <div element="ID_ZSTORM_REDDIT_CLASS_FEATURE_CHRONOMANCER_SPELL_MASTERY" />
      <div element="ID_ZSTORM_REDDIT_CLASS_FEATURE_CHRONOMANCER_SIGNATURE_SPELLS" />
      <div element="ID_ZSTORM_REDDIT_CLASS_FEATURE_CHRONOMANCER_ABILITYSCOREIMPROVEMENT_CHRONOMANCER" />
      <div element="ID_ZSTORM_REDDIT_CLASS_FEATURE_CHRONOMANCER_WHEEL_OF_TIME_FEATURE" />
      <div element="ID_ZSTORM_REDDIT_CLASS_FEATURE_CHRONOMANCER_TIMELESS_BODY_FEATURE" />
      <div element="ID_ZSTORM_REDDIT_CLASS_FEATURE_CHRONOMANCER_REWIND" />
      <div element="ID_ZSTORM_REDDIT_CLASS_FEATURE_CHRONOMANCER_AGELESS_LINGUISTICS_FEATURE" />
      <div element="ID_ZSTORM_REDDIT_CLASS_FEATURE_CHRONOMANCER_LIFELONG_JOURNEY_FEATURE" />
      <div element="ID_ZSTORM_REDDIT_CLASS_FEATURE_CHRONOMANCER_ABILITYSCOREIMPROVEMENT_CHRONOMANCER" />
      <div element="ID_ZSTORM_REDDIT_CLASS_FEATURE_CHRONOMANCER_TIME_ANOMALY" />
      <div element="ID_ZSTORM_REDDIT_CLASS_FEATURE_CHRONOMANCER_HYPERSONIC_SPEED" />
      <div element="ID_ZSTORM_REDDIT_CLASS_FEATURE_CHRONOMANCER_ABILITYSCOREIMPROVEMENT_CHRONOMANCER" />
      <div element="ID_ZSTORM_REDDIT_CLASS_FEATURE_CHRONOMANCER_LIFELONG_JOURNEY_FEATURE" />
      <div element="ID_ZSTORM_REDDIT_CLASS_FEATURE_CHRONOMANCER_LORD_OF_TIME" />
      <div element="ID_ZSTORM_REDDIT_CLASS_FEATURE_CHRONOMANCER_TIMELESS_BODY_FEATURE" />
      <div element="ID_ZSTORM_REDDIT_CLASS_FEATURE_CHRONOMANCER_WHEEL_OF_TIME_FEATURE" />
      <div element="ID_ZSTORM_REDDIT_CLASS_FEATURE_CHRONOMANCER_ABILITYSCOREIMPROVEMENT_CHRONOMANCER" />
      <div element="ID_ZSTORM_REDDIT_CLASS_FEATURE_CHRONOMANCER_UNDO_TIMELINE" />
    </description>
    <sheet display="false">
      <description>A mage capable of bending time and space.</description>
    </sheet>
    <setters>
      <set name="short">A mage capable of bending time and space.</set>
      <set name="hd">d6</set>
    </setters>
    <rules>
        <grant type="Grants" id="ID_INTERNAL_GRANT_MULTICLASS_SPELLCASTING_SLOTS_FULL" requirements="ID_INTERNAL_GRANT_MULTICLASS"/>

      <grant type="Proficiency" id="ID_PROFICIENCY_WEAPON_PROFICIENCY_DAGGER" requirements="!ID_ZSTORM_REDDIT_MULTICLASS_CHRONOMANCER"/>
      <grant type="Proficiency" id="ID_PROFICIENCY_WEAPON_PROFICIENCY_QUARTERSTAFF" requirements="!ID_ZSTORM_REDDIT_MULTICLASS_CHRONOMANCER"/>
      <grant type="Proficiency" id="ID_PROFICIENCY_WEAPON_PROFICIENCY_SHORTSWORD" requirements="!ID_ZSTORM_REDDIT_MULTICLASS_CHRONOMANCER"/>
      
      <grant type="Proficiency" id="ID_PROFICIENCY_SAVINGTHROW_INTELLIGENCE" requirements="!ID_ZSTORM_REDDIT_MULTICLASS_CHRONOMANCER"/>
      <grant type="Proficiency" id="ID_PROFICIENCY_SAVINGTHROW_WISDOM" requirements="!ID_ZSTORM_REDDIT_MULTICLASS_CHRONOMANCER"/>

      <select type="Proficiency" name="Skill Proficiency (Chronomancer)" supports="Skill,Chronomancer" number="2" requirements="!ID_ZSTORM_REDDIT_MULTICLASS_CHRONOMANCER"/>
      
      <grant type="Class Feature" id="ID_ZSTORM_REDDIT_CLASS_FEATURE_CHRONOMANCER_AGELESS_LINGUISTICS" level="1"/>
      <grant type="Class Feature" id="ID_ZSTORM_REDDIT_CLASS_FEATURE_CHRONOMANCER_SPELLCASTING_CHRONOMANCER" level="1"/>
      <grant type="Class Feature" id="ID_ZSTORM_REDDIT_CLASS_FEATURE_CHRONOMANCER_WHEEL_OF_TIME" level="2"/>
      <grant type="Class Feature" id="ID_ZSTORM_REDDIT_CLASS_FEATURE_CHRONOMANCER_TIMELESS_BODY" level="2"/>
      <grant type="Class Feature" id="ID_ZSTORM_REDDIT_CLASS_FEATURE_CHRONOMANCER_LIFELONG_JOURNEY" level="3"/>
      <grant type="Class Feature" id="ID_ZSTORM_REDDIT_CLASS_FEATURE_CHRONOMANCER_ABILITYSCOREIMPROVEMENT_CHRONOMANCER" level="4"/>
      <grant type="Class Feature" id="ID_ZSTORM_REDDIT_CLASS_FEATURE_CHRONOMANCER_POCKET_OF_ETERNITY" level="5"/>
      <grant type="Class Feature" id="ID_ZSTORM_REDDIT_CLASS_FEATURE_CHRONOMANCER_LIFELONG_JOURNEY_FEATURE" level="6"/>
      <grant type="Class Feature" id="ID_ZSTORM_REDDIT_CLASS_FEATURE_CHRONOMANCER_AGELESS_LINGUISTICS_FEATURE" level="6"/>
      <grant type="Class Feature" id="ID_ZSTORM_REDDIT_CLASS_FEATURE_CHRONOMANCER_ABILITYSCOREIMPROVEMENT_CHRONOMANCER" level="8"/>
      <grant type="Class Feature" id="ID_ZSTORM_REDDIT_CLASS_FEATURE_CHRONOMANCER_WHEEL_OF_TIME_FEATURE" level="9"/>
      <grant type="Class Feature" id="ID_ZSTORM_REDDIT_CLASS_FEATURE_CHRONOMANCER_TIMELESS_BODY_FEATURE" level="9"/>
      <grant type="Class Feature" id="ID_ZSTORM_REDDIT_CLASS_FEATURE_CHRONOMANCER_REWIND" level="10"/>
      <grant type="Class Feature" id="ID_ZSTORM_REDDIT_CLASS_FEATURE_CHRONOMANCER_AGELESS_LINGUISTICS_FEATURE" level="10"/>
      <grant type="Class Feature" id="ID_ZSTORM_REDDIT_CLASS_FEATURE_CHRONOMANCER_LIFELONG_JOURNEY_FEATURE" level="11"/>
      <grant type="Class Feature" id="ID_ZSTORM_REDDIT_CLASS_FEATURE_CHRONOMANCER_ABILITYSCOREIMPROVEMENT_CHRONOMANCER" level="12"/>
      <grant type="Class Feature" id="ID_ZSTORM_REDDIT_CLASS_FEATURE_CHRONOMANCER_TIME_ANOMALY" level="13"/>
      <grant type="Class Feature" id="ID_ZSTORM_REDDIT_CLASS_FEATURE_CHRONOMANCER_HYPERSONIC_SPEED" level="15"/>
      <grant type="Class Feature" id="ID_ZSTORM_REDDIT_CLASS_FEATURE_CHRONOMANCER_ABILITYSCOREIMPROVEMENT_CHRONOMANCER" level="16"/>
      <grant type="Class Feature" id="ID_ZSTORM_REDDIT_CLASS_FEATURE_CHRONOMANCER_LIFELONG_JOURNEY_FEATURE" level="17"/>
      <grant type="Class Feature" id="ID_ZSTORM_REDDIT_CLASS_FEATURE_CHRONOMANCER_LORD_OF_TIME" level="17"/>
      <grant type="Class Feature" id="ID_ZSTORM_REDDIT_CLASS_FEATURE_CHRONOMANCER_TIMELESS_BODY_FEATURE" level="18"/>
      <grant type="Class Feature" id="ID_ZSTORM_REDDIT_CLASS_FEATURE_CHRONOMANCER_WHEEL_OF_TIME_FEATURE" level="18"/>
      <grant type="Class Feature" id="ID_ZSTORM_REDDIT_CLASS_FEATURE_CHRONOMANCER_ABILITYSCOREIMPROVEMENT_CHRONOMANCER" level="19"/>
      <grant type="Class Feature" id="ID_ZSTORM_REDDIT_CLASS_FEATURE_CHRONOMANCER_UNDO_TIMELINE" level="20"/>
    </rules>
    <multiclass id="ID_ZSTORM_REDDIT_MULTICLASS_CHRONOMANCER">
      <prerequisite>Intelligence 13</prerequisite>
      <requirements>[int:14],[wis:14]</requirements>
      <setters>
        <set name="multiclass proficiencies">—</set>
      </setters>
      <rules>
        <grant type="Grants" id="ID_INTERNAL_GRANT_MULTICLASS" />
      </rules>
    </multiclass>
  </element>
  <element name="Spellcasting" type="Class Feature" source="Zst0rm" id="ID_ZSTORM_REDDIT_CLASS_FEATURE_CHRONOMANCER_SPELLCASTING_CHRONOMANCER">
    <description>
      <p>As a conduit of the ebb and flow of time, you can cast chronomancer spells. See chapter 10 of the Player’s Handbook for the general rules of spellcasting and you can see the specific chronomancer spell lists at the end of this document.</p>
      <h5>CANTRIPS</h5>
      <p>At 1st level, you know three cantrips of your choice from the Chronomancer spell list. You learn additional Chronomancer cantrips of your choice at higher levels, as shown in the Cantrips Known column of the Chronomancer table.</p>
      <h5>PREPARING AND CASTING SPELLS</h5>
      <p>The Chronomancer table shows how many spell slots you have to cast your spells of 1st level and higher. To cast one of these spells, you must expend a slot of the spell’s level or higher. You regain all expended spell slots when you finish a long rest.</p>
      <p>You prepare the list of Chronomancer spells that are available for you to cast. To do so, choose a number of Chronomancer spells from your spellbook equal to your Wisdom modifier + your Chronomancer level (minimum of one spell). The spells must be of a level for which you have spell slots.</p>
      <p>For example, if you’re a 3rd-level Chronomancer, you have four 1st-level and two 2nd-level spell slots. With an Intelligence of 16, your list of prepared spells can include six spells of 1st or 2nd level, in any combination, chosen from your spellbook. If you prepare the 1st-level spell magic missile, you can cast it using a 1st-level or a 2nd-level slot. Casting the spell doesn’t remove it from your list of prepared spells.</p>
      <p>You can change your list of prepared spells when you finish a long rest. Preparing a new list of Chronomancer spells requires time spent studyingthe ebb and memorizing the incantations and gestures you must make to cast the spell: at least 1 minute per spell level for each spell on your list.</p>
      <h5>SPELLCASTING ABILITY</h5>
      <p>Wisdom is your spellcasting ability for chronomancer spells, since the power of your magic relies of your eternal studies of time. You use your Wisdom whenever a spell refers to your spellcasting ability. In addition, you use your Wisdom modifier when setting the saving throw DC for a chronomancer spell you cast and when making an attack roll with one.</p>
      <p>
        <strong>Spell save DC</strong> = 8 + your proficiency bonus + your Wisdom modifier
      </p>
      <p>
        <strong>Spell attack modifier</strong> = your proficiency bonus + your Wisdom modifier
      </p>
      <h5>SPELLCASTING FOCUS</h5>
      <p>You are attuned with your gaming set and use it as a spellcasting focus for your chronomancer spells</p>
      <h5>LEARNING SPELLS OF 1ST LEVEL AND HIGHER</h5>
      <p>Each time you gain a Chronomancer level, you can add two Chronomancer spells of your choice to your spellbook for free. Each of these spells must be of a level for which you have spell slots, as shown on the Chronomancer table. On your adventures, you might find other spells that you can add to your spellbook (see the “Your Spellbook” sidebar).</p>
    </description>
    <sheet display="true">
      <description>You can prepare {{Chronomancer:spellcasting:prepare}} spells from your known spells. You use an arcane focus to cast spells.</description>
    </sheet>
    <sheet desplay="true">
      <description>Your spell save DC is {{spellsave:dc}}</description>
    </sheet>
    <rules>
      <stat name="spellsave:dc" value="8" />
      <stat name="spellsave:dc" value="proeficiency" />
      <stat name="spellsave:dc" value="wisdom:modifier" />
	  </rules>
    <spellcasting name="Chronomancer" ability="Wisdom" prepare="true">
      <list>Chronomancer</list>
    </spellcasting>
    <rules>
      <grant type="Proficiency" id="ID_INTERNAL_PROFICIENCY_SPELLFOCUS_GROUP_ARCANE_FOCUS" />

      <stat name="Chronomancer:spellcasting:slots:1" value="2" level="1" />
      <stat name="Chronomancer:spellcasting:slots:1" value="1" level="2" />
      <stat name="Chronomancer:spellcasting:slots:1" value="1" level="3" />      
      <stat name="Chronomancer:spellcasting:slots:2" value="2" level="3" />
      <stat name="Chronomancer:spellcasting:slots:2" value="1" level="4" />
      <stat name="Chronomancer:spellcasting:slots:3" value="2" level="5" />
      <stat name="Chronomancer:spellcasting:slots:3" value="1" level="6" />
      <stat name="Chronomancer:spellcasting:slots:4" value="1" level="7" />
      <stat name="Chronomancer:spellcasting:slots:4" value="1" level="8" />
      <stat name="Chronomancer:spellcasting:slots:4" value="1" level="9" />
      <stat name="Chronomancer:spellcasting:slots:5" value="1" level="9" />
      <stat name="Chronomancer:spellcasting:slots:5" value="1" level="10" />
      <stat name="Chronomancer:spellcasting:slots:5" value="1" level="18" />
      <stat name="Chronomancer:spellcasting:slots:6" value="1" level="11" />
      <stat name="Chronomancer:spellcasting:slots:6" value="1" level="19" />
      <stat name="Chronomancer:spellcasting:slots:7" value="1" level="13" />
      <stat name="Chronomancer:spellcasting:slots:7" value="1" level="20" />
      <stat name="Chronomancer:spellcasting:slots:8" value="1" level="15" />
      <stat name="Chronomancer:spellcasting:slots:9" value="1" level="17" />

      <stat name="Chronomancer:spellcasting:prepare" value="wisdom:modifier" />
      <stat name="Chronomancer:spellcasting:prepare" value="level:Chronomancer" />

      <select type="Spell" name="Cantrip (Chronomancer)" supports="$(spellcasting:list), 0" level="1" number="2" spellcasting="Chronomancer" />
      <select type="Spell" name="Cantrip (Chronomancer)" supports="$(spellcasting:list), 0" level="3" number="1" spellcasting="Chronomancer" />
      <select type="Spell" name="Cantrip (Chronomancer)" supports="$(spellcasting:list), 0" level="10" number="1" spellcasting="Chronomancer" />
      
      <select type="Spell" name="Spellbook (Chronomancer)" supports="$(spellcasting:list), 1" level="1" number="6" spellcasting="Chronomancer" />
      <select type="Spell" name="Spellbook (Chronomancer)" supports="$(spellcasting:list), $(spellcasting:slots)" level="2" number="2" spellcasting="Chronomancer" />
      <select type="Spell" name="Spellbook (Chronomancer)" supports="$(spellcasting:list), $(spellcasting:slots)" level="3" number="2" spellcasting="Chronomancer" />
      <select type="Spell" name="Spellbook (Chronomancer)" supports="$(spellcasting:list), $(spellcasting:slots)" level="4" number="2" spellcasting="Chronomancer" />
      <select type="Spell" name="Spellbook (Chronomancer)" supports="$(spellcasting:list), $(spellcasting:slots)" level="5" number="2" spellcasting="Chronomancer" />
      <select type="Spell" name="Spellbook (Chronomancer)" supports="$(spellcasting:list), $(spellcasting:slots)" level="6" number="2" spellcasting="Chronomancer" />
      <select type="Spell" name="Spellbook (Chronomancer)" supports="$(spellcasting:list), $(spellcasting:slots)" level="7" number="2" spellcasting="Chronomancer" />
      <select type="Spell" name="Spellbook (Chronomancer)" supports="$(spellcasting:list), $(spellcasting:slots)" level="8" number="2" spellcasting="Chronomancer" />
      <select type="Spell" name="Spellbook (Chronomancer)" supports="$(spellcasting:list), $(spellcasting:slots)" level="9" number="2" spellcasting="Chronomancer" />
      <select type="Spell" name="Spellbook (Chronomancer)" supports="$(spellcasting:list), $(spellcasting:slots)" level="10" number="2" spellcasting="Chronomancer" />
      <select type="Spell" name="Spellbook (Chronomancer)" supports="$(spellcasting:list), $(spellcasting:slots)" level="11" number="2" spellcasting="Chronomancer" />
      <select type="Spell" name="Spellbook (Chronomancer)" supports="$(spellcasting:list), $(spellcasting:slots)" level="12" number="2" spellcasting="Chronomancer" />
      <select type="Spell" name="Spellbook (Chronomancer)" supports="$(spellcasting:list), $(spellcasting:slots)" level="13" number="2" spellcasting="Chronomancer" />
      <select type="Spell" name="Spellbook (Chronomancer)" supports="$(spellcasting:list), $(spellcasting:slots)" level="14" number="2" spellcasting="Chronomancer" />
      <select type="Spell" name="Spellbook (Chronomancer)" supports="$(spellcasting:list), $(spellcasting:slots)" level="15" number="2" spellcasting="Chronomancer" />
      <select type="Spell" name="Spellbook (Chronomancer)" supports="$(spellcasting:list), $(spellcasting:slots)" level="16" number="2" spellcasting="Chronomancer" />
      <select type="Spell" name="Spellbook (Chronomancer)" supports="$(spellcasting:list), $(spellcasting:slots)" level="17" number="2" spellcasting="Chronomancer" />
      <select type="Spell" name="Spellbook (Chronomancer)" supports="$(spellcasting:list), $(spellcasting:slots)" level="18" number="2" spellcasting="Chronomancer" />
      <select type="Spell" name="Spellbook (Chronomancer)" supports="$(spellcasting:list), $(spellcasting:slots)" level="19" number="2" spellcasting="Chronomancer" />
      <select type="Spell" name="Spellbook (Chronomancer)" supports="$(spellcasting:list), $(spellcasting:slots)" level="20" number="2" spellcasting="Chronomancer" />
    </rules>
  </element>

  <element name="Ageless linguistics" type="Class Feature" source="Zst0rm" id="ID_ZSTORM_REDDIT_CLASS_FEATURE_CHRONOMANCER_AGELESS_LINGUISTICS">
    <description>
      <p>At 1st level, you can learn some of the oldest languages in the realm. You gain proficiency in 2 exotic languages. At 6th level you gain proficiency in 2 more exotic languages. And then at 10th level YOu gain proficiency in another 2 more exotic languages.</p>
    </description>
    <sheet>
      <description>Gain at 1st lvl 2 exotic languages, 6th level 2 more and 10th level 2 more</description>
    </sheet>
  </element>

  <element name="Wheel of time" type="Class Feature" source="Zst0rm" id="ID_ZSTORM_REDDIT_CLASS_FEATURE_CHRONOMANCER_WHEEL_OF_TIME">
    <description>
      <p>At 2nd level your studies allow you to spin the wheel of time to alter the fate of yourself, an ally or an enemy. Your access to this bend in time is represented by fate dice. You have fate dice equal To your proficiency bonus + half of your chronomancer level (rounding down). For example a 2nd level chronomancer has 3 fate dice, whereas a 9th level chronomancer has 8 fate dice.</p>
      <p>You can expend fate dice for a variety of uses. You know how to bend time to do the following: Accelerate, Decelerate and Surge.</p>
      <p>When you expend fate dice, it is unavailable until you finish a long rest at which point you regain all expended fate dice by rewinding the wheel of time.</p>
      <p>Some of your Wheel of Time features may require your target to make a saving throw to resist the features effects. The saving throw is your spell save DC which you can calculate in the Spellcasting Ability section previously.</p>
      <h6>Accelerate</h6>
      <p class="indent">As a bonus action you can expend a fate dice to hasten a targets actions and do multiple actions on the targets next turn. You roll 1d4 and the target gains additional actions equal to the result. You cannot use any of these extra actions for Accelerate or Surge. You can use this once per long rest. At 9th level you can use this twice per long rest, and at 18th level you can use Accelerate 3 times per long rest.</p>
      <h6>Decelerate</h6>
      <p class="indent">As a reaction to being damaged by an enemy you can delay the wounds inflicted by expending a fate dice. fate dice. You roll 1d4 and do not take the damage that would of been inflicted for that amount of rounds. The creature damaging you can make a Wisdom saving throw to ignore the effect and break the bend in time.</p>
      <p>For example, you roll a 3 and do not take the damage until 3 rounds has passed. This includes the round where the round where you used Decelerate.</p>
      <h6>Surge</h6>
      <p class="indent">As an action you can expend a fate dice to take an additional action in the next round. You cannot use this additional action to cast any spell of 4th-level or higher. The action gained by surge cannot be used for Surge again.</p>
    </description>
    <sheet usage="1/Long Rest">
    <description>
      <p>At 2nd level you have fate dice equal to {{fate:dice}} and the following abilities:</p>
      <p>Accelerate, spend a fate dice and give 1d4 more actions to target per long rest, at 9th twice per long rest, at 18th three times per long rest</p>
      <p>Decelerate, as a reaction delay the wounds for 1d4 turns, enemy creature can make a WIS saving throw and ignore the effect</p>
      <p>Surge, As an action spend one fate dice and gain one aditional action for your next turn, not usable with surge again</p>
    </description>
    </sheet>
    <rules>
    <stat name="fate:dice" value="proeficiency" />
    <stat name="fate:dice" value="level:chronomancer" />
    </rules>
  </element>

    <element name="Timeless body" type="Class Feature" source="Zst0rm" id="ID_ZSTORM_REDDIT_CLASS_FEATURE_CHRONOMANCER_TIMELESS_BODY">
    <description>
      <p>At 2nd level, your intense studies with time and your ability to control and alter it makes you keep your youthful looks. You still can die of old age, however. At 9th level, your body is immune to the frailty of old age, and cannot be aged magically. At 18th level, you no longer need food or food or water.</p>
    </description>
    <sheet>
      <description>At 2nd level your youth is with you. At 9th level your body can't age by any means and at 18 you don't need food or water</description>
    </sheet>
  </element>

  <element name="Lifelong journey" type="Class Feature" source="Zst0rm" id="ID_ZSTORM_REDDIT_CLASS_FEATURE_CHRONOMANCER_LIFELONG_JOURNEY"> 
  <description>
  <p>When you reach 3rd level, you become attuned with a certain timeline of events. These timelines are: 3351 B.C., 253 A.D., 1877 A.D., all of which  are detailled at the end of the class description, before the chronomancer spell lists. Your Lifelong Journey grants you features at 3rd level and again at 6th, 11th, and 17th l and again at 6th, 11th, and 17th level.</p>
  </description>
    <rules>
      <select type="Archetype" name="Lifelong journey" supports="Lifelong journey" />
    </rules>
  </element>

  <element name="Ability Score Improvement (Chronomancer)" type="Class Feature" source="Zst0rm" id="ID_ZSTORM_REDDIT_CLASS_CHRONOMANCER_ABILITYSCOREIMPROVEMENT_CHRONOMANCER">
    <description>
      <p>When you reach 4th level, and again at 8th, 12th, 16th, and 19th level, you can increase one ability score of your choice by 2, or you can increase two ability scores of your choice by 1. As normal, you can’t increase an ability score above 20 using this feature.</p>
    </description>
    <sheet display="false" />
    <rules>
      <!-- <grant type="Class Feature" id="ID_INTERNAL_CLASS_FEATURE_ASI_4_CHRONOMANCER" level="4" requirements="!ID_INTERNAL_OPTION_ALLOW_FEATS" />
      <grant type="Class Feature" id="ID_INTERNAL_CLASS_FEATURE_ASI_8_CHRONOMANCER" level="8" requirements="!ID_INTERNAL_OPTION_ALLOW_FEATS" />
      <grant type="Class Feature" id="ID_INTERNAL_CLASS_FEATURE_ASI_12_CHRONOMANCER" level="12" requirements="!ID_INTERNAL_OPTION_ALLOW_FEATS" />
      <grant type="Class Feature" id="ID_INTERNAL_CLASS_FEATURE_ASI_16_CHRONOMANCER" level="16" requirements="!ID_INTERNAL_OPTION_ALLOW_FEATS" />
      <grant type="Class Feature" id="ID_INTERNAL_CLASS_FEATURE_ASI_19_CHRONOMANCER" level="19" requirements="!ID_INTERNAL_OPTION_ALLOW_FEATS" /> -->
      <select type="Class Feature" name="Improvement Option (Chronomancer 4)" supports="Improvement Option,CHRONOMANCER,4" level="4" />
      <select type="Class Feature" name="Improvement Option (Chronomancer 8)" supports="Improvement Option,CHRONOMANCER,8" level="8" />
      <select type="Class Feature" name="Improvement Option (Chronomancer 12)" supports="Improvement Option,CHRONOMANCER,12" level="12" />
      <select type="Class Feature" name="Improvement Option (Chronomancer 16)" supports="Improvement Option,CHRONOMANCER,16" level="16" />
      <select type="Class Feature" name="Improvement Option (Chronomancer 19)" supports="Improvement Option,CHRONOMANCER,19" level="19" />
    </rules>
  </element>
  
  <element name="Pocket of eternity" type="Class Feature" source="Zst0rm" id="ID_ZSTORM_REDDIT_CLASS_FEATURE_CHRONOMANCER_POCKET_OF_ETERNITY">
    <description>
      <p>At 5th level, in your resourcefulness you have created an eternal pocket of time that you can rely upon when in need. On your turn, you can use a bonus action to regain hit points equal to 1d8 + chronomancer level + proficiency bonus.</p>
      <p>Once you use this feature, you must finish a short or long rest before you can use it again.</p>
    </description>
    <sheet usage="1/Long Rest">
      <description>Once per long rest On your turn, as a bonus action regain hit points equal to 1d8 + chronomancer level + proficiency bonus.</description>
    </sheet>
  </element>

  <element name="Rewind" type="Class Feature" source="Zst0rm" id="ID_ZSTORM_REDDIT_CLASS_FEATURE_CHRONOMANCER_REWIND">
    <description>
      <p>At 10th level, if you have one fate die remaining, you can as an action expend and roll that fate die. You gain a number of fate dice equal to 1d4+2. This feature recharges at the end of a long rest.</p>
    </description>
    <sheet usage="1/Long Rest">
      <description>You gain a number of fate dice equal to 1d4+2. This feature recharges at the end of a long rest.</description>
    </sheet>
  </element>

  <element name="Time anomaly" type="Class Feature" source="Zst0rm" id="ID_ZSTORM_REDDIT_CLASS_FEATURE_CHRONOMANCER_TIME_ANOMALY">
    <description>
      <p>At 13th level, when you cast a spell that has a casting time of 1 action, you can change the casting time to 1 bonus action for this casting. After you use this ability 3 times, you must finish a long rest before using it again.</p>
    </description>
    <sheet usage="1/Long Rest">
      <description>Cast a spell using a bonus action instrad of an action, Do this 3 times before a long rest</description>
    </sheet>
  </element>

  <element name="Hypersonic Speed" type="Class Feature" source="Zst0rm" id="ID_ZSTORM_REDDIT_CLASS_FEATURE_CHRONOMANCER_HYPERSONIC_SPEED">
    <description>
      <p>Upon reaching 15th level, your awareness to danger reaches a hypersonic clarity. You add +5 to your initiative rolls.</p>
    </description>
    <sheet>
      <description>Add +5 to initiative</description>
    </sheet>
    <rules>
    <stat name="chronomancer:initiative" value="5" bonus="initiative" level="15" />
    </rules>
  </element>

  <element name="Time Lord" type="Class Feature" source="Zst0rm" id="ID_ZSTORM_REDDIT_CLASS_FEATURE_CHRONOMANCER_TIME_LORD">
    <description>
      <p>Once the chronomancer reaches 17th level you are considered to be a Time Lord. This allows the chronomancer to predict a favorable outcome from a battle. The chronomancer can now roll a 19 or 20 to critically hit on attacks and you add +1 to your spell save DC.</p>
    </description>
    <sheet>
      <description>When you roll 19 or 20 its a crit, also add 1+ to the spell save DC</description>
    </sheet>
    <rules>
    <stat name="spellsave:dc" value="1" />
    </rules>
  </element>

  <element name="Undo Timeline" type="Class Feature" source="Zst0rm" id="ID_ZSTORM_REDDIT_CLASS_FEATURE_CHRONOMANCER_UNDO_TIMELINE">
    <description>
      <p>Upon reaching 20th level, you gain the ability to undo a specific timeline, taking all actions of up to 8 targets back in time (up to 3 hours prior). All experience and items gained within that time are lost. All spell slots that were used within the time frame become unused. You can only use this feature once feature once every 7 long rests (a week).</p>
    </description>
    <sheet usage="1/Long Rest">
      <description>Return time for 8 creatures, they regain everthing they've used, you can't use this until you pass 7 long rests</description>
    </sheet>
  </element>




<element name="3351 BC" type="Archetype" source="Zst0rm" id="ID_ZSTORM_REDDIT_ARCHETYPE_CHRONOMANCER_3351BC">
  <supports>Lifelong journey</supports>
  <description>
    <p>You travelled back to a time where magic and miracles were rich throughout the land. Upon spending countless years in this timeline you are more attuned to magic than ever before.</p>
    <div element="ID_ZSTORM_REDDIT_ARCHETYPE_FEATURE_CHRONOMANCER__3351BC_EPOCH_CONTINUUM" />
    <div element="ID_ZSTORM_REDDIT_ARCHETYPE_FEATURE_CHRONOMANCER_3351BC_ANCIENT_RESEARCH" />
    <div element="ID_ZSTORM_REDDIT_ARCHETYPE_FEATURE_CHRONOMANCER_3351BC_FARE_RENEWED" />
    <div element="ID_ZSTORM_REDDIT_ARCHETYPE_FEATURE_CHRONOMANCER_3351BC_TIMELESS_VISAGE" />
  </description>
  <sheet>
    <description>You travelled back to a time where magic and miracles were rich throughout the land. Upon spending countless years in this timeline you are more attuned to magic than ever before.</description>
  </sheet>
  <rules>
    <grant type="Archetype" id="ID_ZSTORM_REDDIT_ARCHETYPE_FEATURE_CHRONOMANCER__3351BC_EPOCH_CONTINUUM" level="3"/>
    <grant type="Archetype" id="ID_ZSTORM_REDDIT_ARCHETYPE_FEATURE_CHRONOMANCER_3351BC_ANCIENT_RESEARCH" level="6"/>
    <grant type="Archetype" id="ID_ZSTORM_REDDIT_ARCHETYPE_FEATURE_CHRONOMANCER_3351BC_FARE_RENEWED" level="11"/>
    <grant type="Archetype" id="ID_ZSTORM_REDDIT_ARCHETYPE_FEATURE_CHRONOMANCER_3351BC_TIMELESS_VISAGE" level="17"/>
  </rules>
</element>

<element name="Epoch Continuum" type="Archetype Feature" source="Zst0rm" id="ID_ZSTORM_REDDIT_ARCHETYPE_FEATURE_CHRONOMANCER_3351BC_EPOCH_CONTINUUM">
  <description>
    <p>Starting when you choose this journey at 3rd level, your Bolt of Time cantrip is altered to be Epoch Bolt. When Bolt of Time is altered to be Epoch Bolt it gains these effects:</p>
    <p class="indent">When dealing damage with this spell, in the place of d8’s use 1d4 + 1d4 for damage rolls. For example: Casting Epoch Bolt at 5th level and hitting will deal 4d4 force damage.</p>
    <p class="indent">The creature hit cannot take reactions until your next turn if they fail a Wisdom saving throw.</p>
    <p class="indent">You gain an advantage on spell attack rolls with Epoch Bolt.</p>
  </description>
  <sheet>
    <description>The cantrip bolt of time changes name to Epch bolt and rolls twice the d4 instead of d8, also when hit creature can't take reactions and you have advantage on atk with this cantrip</description>
  </sheet>
</element>
<element name="Ancient Research" type="Archetype Feature" source="Zst0rm" id="ID_ZSTORM_REDDIT_ARCHETYPE_FEATURE_CHRONOMANCER_3351BC_ANCIENT_RESEARCH">
  <description>
    <p>At 6th level. you gain +2 to your Wisdom stat. This cannot make the stat total go over 20. You apply your proficiency bonus to the damage of your spells.</p>
  </description>
  <sheet>
        <description>At 6th level. you gain +2 to your Wisdom stat. This cannot make the stat total go over 20. You apply your proficiency bonus to the damage of your spells.</description>
</sheet>
  <rules>
	<stat name="wisdom" value="2" />
  </rules>
</element>
<element name="Fate Renewed" type="Archetype Feature" source="Zst0rm" id="ID_ZSTORM_REDDIT_ARCHETYPE_FEATURE_CHRONOMANCER_3351BC_FATE_RENEWED">
  <description>
    <p>Beginning at 11th level, you can expend a fate dice as a bonus action to heal a creature. It gains hitpoints equal to 1d6+1 times your chronomancer level. You must finish a long rest before you can use this feature again.</p>
  </description>
  <sheet>
    <description>You can expend a fate dice as a bonus action to heal a creature. It gains hitpoints equal to 1d6+1 times your chronomancer level. You must finish a long rest before you can use this feature again.</description>
  </sheet>
</element>
<element name="Timeless visage" type="Archetype Feature" source="Player’s Handbook" id="ID_ZSTORM_REDDIT_ARCHETYPE_FEATURE_CHRONOMANCER_3351BC_TIMELESS_VISAGE">
  <description>
    <p>Once 17th level is obtained, you gain the ability to create a timeless visage of yourself acting like a clone. This timeless visage cannot expend fate dice. However it can attack and cast cantrips at your telepathic command.</p>
  <p class="indent">When you create a timeless visage you must roll its initiat roll its initiative. The timeless visage is controlled by you and does not require your concentration. If you do not give the visage commands it will not move or react. The visage uses all your statistics, it does not gain your feats and has hitpoints equal to one half of your total hitpoints. You must finish a long rest before you can use this feature again.</p>
  </description>
  <sheet usage="1/Long Rest">
    <description>Create a time copy of yourself with all your abilties and half your hit points</description>
  </sheet>
  </element>


</elements>
